{"cameraMode":{"drawMode":0,"name":"Shaded","section":"Shading Mode"},"sceneLighting":false,"audioPlay":false,"sceneViewState":{"m_AlwaysRefresh":false,"showFog":false,"showSkybox":true,"showFlares":true,"showImageEffects":true,"showParticleSystems":true,"showVisualEffectGraphs":true,"m_FxEnabled":true},"in2DMode":false,"pivot":{"x":296.7484436035156,"y":-264.12060546875,"z":867.9503784179688},"rotation":{"x":-0.14918047189712525,"y":-0.17287413775920869,"z":0.02648925594985485,"w":-0.9732340574264526},"size":459.74774169921877,"orthographic":false}